odoo/addons/account_invoice_inter_company_sale/README.rst
odoo/addons/account_invoice_inter_company_sale/__init__.py
odoo/addons/account_invoice_inter_company_sale/__manifest__.py
odoo/addons/account_invoice_inter_company_sale/i18n/account_invoice_inter_company_sale.pot
odoo/addons/account_invoice_inter_company_sale/i18n/es.po
odoo/addons/account_invoice_inter_company_sale/i18n/it.po
odoo/addons/account_invoice_inter_company_sale/models/__init__.py
odoo/addons/account_invoice_inter_company_sale/models/account_move.py
odoo/addons/account_invoice_inter_company_sale/readme/CONFIGURE.rst
odoo/addons/account_invoice_inter_company_sale/readme/CONTRIBUTORS.rst
odoo/addons/account_invoice_inter_company_sale/readme/DESCRIPTION.rst
odoo/addons/account_invoice_inter_company_sale/readme/ROADMAP.rst
odoo/addons/account_invoice_inter_company_sale/static/description/icon.png
odoo/addons/account_invoice_inter_company_sale/static/description/index.html
odoo/addons/account_invoice_inter_company_sale/views/account_move_views.xml
odoo14_addon_account_invoice_inter_company_sale-14.0.1.0.1.dev8.dist-info/METADATA
odoo14_addon_account_invoice_inter_company_sale-14.0.1.0.1.dev8.dist-info/WHEEL
odoo14_addon_account_invoice_inter_company_sale-14.0.1.0.1.dev8.dist-info/top_level.txt
odoo14_addon_account_invoice_inter_company_sale-14.0.1.0.1.dev8.dist-info/RECORD
